playoff_core/__init__.py
playoff_core/data_handler.py
playoff_core/design_handler.py
playoff_core/import_export_playoff.py
playoff_core/utility.py
playoff_core-0.8.3.dist-info/LICENSE
playoff_core-0.8.3.dist-info/METADATA
playoff_core-0.8.3.dist-info/WHEEL
playoff_core-0.8.3.dist-info/top_level.txt
playoff_core-0.8.3.dist-info/RECORD
