Metadata-Version: 2.1
Name: playoff-core
Version: 0.8.3
Summary: Playoff toolbox
Home-page: https://github.com/officina/playoff-core
Author: Mattia Bano
Author-email: dev@officina.cc
License: UNKNOWN
Platform: UNKNOWN
Classifier: Programming Language :: Python :: 3
Classifier: License :: OSI Approved :: MIT License
Classifier: Operating System :: OS Independent
Requires-Dist: Playoff
Requires-Dist: jwt
Requires-Dist: python-dotenv
